readme_executor/__init__.py
readme_executor/_app.py
readme_executor/readme_executor.py
readme_executor-0.9.1.dist-info/entry_points.txt
readme_executor-0.9.1.dist-info/WHEEL
readme_executor-0.9.1.dist-info/METADATA
readme_executor-0.9.1.dist-info/RECORD
