Metadata-Version: 2.1
Name: readme_executor
Version: 0.9.1
Summary: Module to execute tagged Python code blocks in Markdown files
Author-email: Randall Morgan <rmorgan@sensornet.us>
Requires-Python: >=3.7
Classifier: License :: OSI Approved :: GNU Lesser General Public License v2 or later (LGPLv2+)
